MANIFEST.in
README.md
setup.cfg
setup.py
.idea/misc.xml
.idea/modules.xml
.idea/vcs.xml
.idea/workspace.xml
.idea/inspectionProfiles/profiles_settings.xml
morphing_agents/__init__.py
morphing_agents.egg-info/PKG-INFO
morphing_agents.egg-info/SOURCES.txt
morphing_agents.egg-info/dependency_links.txt
morphing_agents.egg-info/requires.txt
morphing_agents.egg-info/top_level.txt
morphing_agents/mujoco/__init__.py
morphing_agents/mujoco/utils.py
morphing_agents/mujoco/ant/__init__.py
morphing_agents/mujoco/ant/base.xml
morphing_agents/mujoco/ant/designs.py
morphing_agents/mujoco/ant/elements.py
morphing_agents/mujoco/ant/env.py
morphing_agents/mujoco/dkitty/__init__.py
morphing_agents/mujoco/dkitty/designs.py
morphing_agents/mujoco/dkitty/elements.py
morphing_agents/mujoco/dkitty/env.py
morphing_agents/mujoco/dog/__init__.py
morphing_agents/mujoco/dog/base.xml
morphing_agents/mujoco/dog/designs.py
morphing_agents/mujoco/dog/elements.py
morphing_agents/mujoco/dog/env.py