Metadata-Version: 2.1
Name: morphing-agents
Version: 1.4
Summary: Collection Of Dynamic Morphology Agents For MuJoCo
Home-page: https://github.com/brandontrabucco/morphing-agents
Author: Brandon Trabucco
Author-email: brandon@btrabucco.com
License: MIT
Download-URL: https://github.com/brandontrabucco/morphing-agents/archive/v1_4.tar.gz
Keywords: MuJoCo,Agents,Dynamic Morphology
Platform: UNKNOWN
Classifier: Intended Audience :: Developers
Classifier: Intended Audience :: Science/Research
Classifier: Topic :: Scientific/Engineering
Classifier: Topic :: Scientific/Engineering :: Artificial Intelligence
Classifier: Topic :: Scientific/Engineering :: Mathematics
Classifier: Topic :: Software Development
Classifier: Topic :: Software Development :: Libraries
Classifier: Topic :: Software Development :: Libraries :: Python Modules
Classifier: License :: OSI Approved :: MIT License
Classifier: Programming Language :: Python :: 3
Classifier: Programming Language :: Python :: 3.5
Classifier: Programming Language :: Python :: 3.6
Classifier: Programming Language :: Python :: 3.7
Classifier: Programming Language :: Python :: 3.8
